{
  "updatedAt": "2026-04-03T23:32:39.769464+09:00",
  "observedLatestAt": "2026-04-03T23:20:00+09:00",
  "prefecture": "和歌山県",
  "element": "monthMax72hPrecip",
  "month": "5",
  "rows": [
    {
      "stationName": "友ケ島",
      "startDate": "2022年5月（令和4年）",
      "ranks": [
        {
          "rank": 1,
          "value": 208.5,
          "date": "2011年5月30日（平成23年）",
          "highlightLive": false,
          "highlightWithinYear": false
        },
        {
          "rank": 2,
          "value": 191.5,
          "date": "2008年5月14日（平成20年）",
          "highlightLive": false,
          "highlightWithinYear": false
        },
        {
          "rank": 3,
          "value": 184,
          "date": "1998年5月19日（平成10年）",
          "highlightLive": false,
          "highlightWithinYear": false
        },
        {
          "rank": 4,
          "value": 105.5,
          "date": "2024年5月30日（令和6年）",
          "highlightLive": false,
          "highlightWithinYear": false
        },
        {
          "rank": 5,
          "value": 90,
          "date": "2014年5月1日（平成26年）",
          "highlightLive": false,
          "highlightWithinYear": false
        },
        {
          "rank": 6,
          "value": 79.5,
          "date": "2010年5月26日（平成22年）",
          "highlightLive": false,
          "highlightWithinYear": false
        },
        {
          "rank": 7,
          "value": 78,
          "date": "2018年5月16日（平成30年）",
          "highlightLive": false,
          "highlightWithinYear": false
        },
        {
          "rank": 8,
          "value": 74,
          "date": "2004年5月16日（平成16年）",
          "highlightLive": false,
          "highlightWithinYear": false
        },
        {
          "rank": 9,
          "value": 74,
          "date": "2001年5月25日（平成13年）",
          "highlightLive": false,
          "highlightWithinYear": false
        },
        {
          "rank": 10,
          "value": 69,
          "date": "2022年5月14日（令和4年）",
          "highlightLive": false,
          "highlightWithinYear": false
        }
      ]
    }
  ]
}
