{
  "updatedAt": "2026-04-28T07:07:54.609391+09:00",
  "observedLatestAt": "2026-04-28T07:00:00+09:00",
  "prefecture": "滋賀県",
  "region": "近畿",
  "element": "dailyPrecip",
  "month": "2",
  "rows": [
    {
      "stationName": "柳ケ瀬",
      "startDate": "1977年2月（昭和52年）",
      "ranks": [
        {
          "rank": 1,
          "value": 70.5,
          "date": "2017年2月11日（平成29年）",
          "_date_raw": "2017/02/11"
        },
        {
          "rank": 2,
          "value": 68,
          "date": "1996年2月2日（平成8年）",
          "_date_raw": "1996/02/02"
        },
        {
          "rank": 3,
          "value": 65,
          "date": "2022年2月5日（令和4年）",
          "_date_raw": "2022/02/05"
        },
        {
          "rank": 4,
          "value": 62,
          "date": "2021年2月15日（令和3年）",
          "_date_raw": "2021/02/15"
        },
        {
          "rank": 5,
          "value": 60,
          "date": "1979年2月24日（昭和54年）",
          "_date_raw": "1979/02/24"
        },
        {
          "rank": 6,
          "value": 58,
          "date": "1987年2月25日（昭和62年）",
          "_date_raw": "1987/02/25"
        },
        {
          "rank": 7,
          "value": 56,
          "date": "2015年2月9日（平成27年）",
          "_date_raw": "2015/02/09"
        },
        {
          "rank": 8,
          "value": 54,
          "date": "2021年2月18日（令和3年）",
          "_date_raw": "2021/02/18"
        },
        {
          "rank": 9,
          "value": 54,
          "date": "2018年2月11日（平成30年）",
          "_date_raw": "2018/02/11"
        },
        {
          "rank": 10,
          "value": 54,
          "date": "2005年2月2日（平成17年）",
          "_date_raw": "2005/02/02"
        }
      ]
    },
    {
      "stationName": "今津",
      "startDate": "1976年2月（昭和51年）",
      "ranks": [
        {
          "rank": 1,
          "value": 52,
          "date": "2021年2月15日（令和3年）",
          "_date_raw": "2021/02/15"
        },
        {
          "rank": 2,
          "value": 47,
          "date": "2012年2月2日（平成24年）",
          "_date_raw": "2012/02/02"
        },
        {
          "rank": 3,
          "value": 46,
          "date": "1979年2月23日（昭和54年）",
          "_date_raw": "1979/02/23"
        },
        {
          "rank": 4,
          "value": 40.5,
          "date": "2010年2月26日（平成22年）",
          "_date_raw": "2010/02/26"
        },
        {
          "rank": 5,
          "value": 40,
          "date": "1990年2月23日（平成2年）",
          "_date_raw": "1990/02/23"
        },
        {
          "rank": 6,
          "value": 40,
          "date": "1982年2月1日（昭和57年）",
          "_date_raw": "1982/02/01"
        },
        {
          "rank": 7,
          "value": 39,
          "date": "2011年2月28日（平成23年）",
          "_date_raw": "2011/02/28"
        },
        {
          "rank": 8,
          "value": 39,
          "date": "1989年2月25日（平成元年）",
          "_date_raw": "1989/02/25"
        },
        {
          "rank": 9,
          "value": 38,
          "date": "2008年2月17日（平成20年）",
          "_date_raw": "2008/02/17"
        },
        {
          "rank": 10,
          "value": 38,
          "date": "1994年2月3日（平成6年）",
          "_date_raw": "1994/02/03"
        }
      ]
    },
    {
      "stationName": "長浜",
      "startDate": "1976年2月（昭和51年）",
      "ranks": [
        {
          "rank": 1,
          "value": 47,
          "date": "2022年2月6日（令和4年）",
          "_date_raw": "2022/02/06"
        },
        {
          "rank": 2,
          "value": 43.5,
          "date": "2022年2月5日（令和4年）",
          "_date_raw": "2022/02/05"
        },
        {
          "rank": 3,
          "value": 43.5,
          "date": "2012年2月2日（平成24年）",
          "_date_raw": "2012/02/02"
        },
        {
          "rank": 4,
          "value": 38,
          "date": "2004年2月22日（平成16年）",
          "_date_raw": "2004/02/22"
        },
        {
          "rank": 5,
          "value": 36.5,
          "date": "2011年2月28日（平成23年）",
          "_date_raw": "2011/02/28"
        },
        {
          "rank": 6,
          "value": 35,
          "date": "1989年2月25日（平成元年）",
          "_date_raw": "1989/02/25"
        },
        {
          "rank": 7,
          "value": 33.5,
          "date": "2020年2月16日（令和2年）",
          "_date_raw": "2020/02/16"
        },
        {
          "rank": 8,
          "value": 33,
          "date": "2017年2月11日（平成29年）",
          "_date_raw": "2017/02/11"
        },
        {
          "rank": 9,
          "value": 33,
          "date": "1985年2月9日（昭和60年）",
          "_date_raw": "1985/02/09"
        },
        {
          "rank": 10,
          "value": 31.5,
          "date": "2021年2月15日（令和3年）",
          "_date_raw": "2021/02/15"
        }
      ]
    },
    {
      "stationName": "朽木平良",
      "startDate": "2007年2月（平成19年）",
      "ranks": [
        {
          "rank": 1,
          "value": 57.5,
          "date": "2021年2月15日（令和3年）",
          "_date_raw": "2021/02/15"
        },
        {
          "rank": 2,
          "value": 53.5,
          "date": "2017年2月10日（平成29年）",
          "_date_raw": "2017/02/10"
        },
        {
          "rank": 3,
          "value": 45,
          "date": "2007年2月2日（平成19年）",
          "_date_raw": "2007/02/02"
        },
        {
          "rank": 4,
          "value": 44,
          "date": "2012年2月18日（平成24年）",
          "_date_raw": "2012/02/18"
        },
        {
          "rank": 5,
          "value": 43.5,
          "date": "2011年2月28日（平成23年）",
          "_date_raw": "2011/02/28"
        },
        {
          "rank": 6,
          "value": 41,
          "date": "2013年2月18日（平成25年）",
          "_date_raw": "2013/02/18"
        },
        {
          "rank": 7,
          "value": 40.5,
          "date": "2014年2月15日（平成26年）",
          "_date_raw": "2014/02/15"
        },
        {
          "rank": 8,
          "value": 36.5,
          "date": "2020年2月16日（令和2年）",
          "_date_raw": "2020/02/16"
        },
        {
          "rank": 9,
          "value": 36.5,
          "date": "2016年2月13日（平成28年）",
          "_date_raw": "2016/02/13"
        },
        {
          "rank": 10,
          "value": 36.5,
          "date": "2012年2月2日（平成24年）",
          "_date_raw": "2012/02/02"
        }
      ]
    },
    {
      "stationName": "米原",
      "startDate": "2002年2月（平成14年）",
      "ranks": [
        {
          "rank": 1,
          "value": 47,
          "date": "2022年2月6日（令和4年）",
          "_date_raw": "2022/02/06"
        },
        {
          "rank": 2,
          "value": 44.5,
          "date": "2022年2月5日（令和4年）",
          "_date_raw": "2022/02/05"
        },
        {
          "rank": 3,
          "value": 44.5,
          "date": "2011年2月28日（平成23年）",
          "_date_raw": "2011/02/28"
        },
        {
          "rank": 4,
          "value": 42,
          "date": "2004年2月22日（平成16年）",
          "_date_raw": "2004/02/22"
        },
        {
          "rank": 5,
          "value": 40,
          "date": "2021年2月15日（令和3年）",
          "_date_raw": "2021/02/15"
        },
        {
          "rank": 6,
          "value": 38.5,
          "date": "2010年2月26日（平成22年）",
          "_date_raw": "2010/02/26"
        },
        {
          "rank": 7,
          "value": 36.5,
          "date": "2020年2月16日（令和2年）",
          "_date_raw": "2020/02/16"
        },
        {
          "rank": 8,
          "value": 29,
          "date": "2012年2月2日（平成24年）",
          "_date_raw": "2012/02/02"
        },
        {
          "rank": 9,
          "value": 28,
          "date": "2008年2月17日（平成20年）",
          "_date_raw": "2008/02/17"
        },
        {
          "rank": 10,
          "value": 27,
          "date": "2008年2月15日（平成20年）",
          "_date_raw": "2008/02/15"
        }
      ]
    },
    {
      "stationName": "南小松",
      "startDate": "1979年2月（昭和54年）",
      "ranks": [
        {
          "rank": 1,
          "value": 64,
          "date": "1985年2月9日（昭和60年）",
          "_date_raw": "1985/02/09"
        },
        {
          "rank": 2,
          "value": 55,
          "date": "1989年2月25日（平成元年）",
          "_date_raw": "1989/02/25"
        },
        {
          "rank": 3,
          "value": 54,
          "date": "1991年2月16日（平成3年）",
          "_date_raw": "1991/02/16"
        },
        {
          "rank": 4,
          "value": 53,
          "date": "1979年2月23日（昭和54年）",
          "_date_raw": "1979/02/23"
        },
        {
          "rank": 5,
          "value": 48,
          "date": "2011年2月28日（平成23年）",
          "_date_raw": "2011/02/28"
        },
        {
          "rank": 6,
          "value": 47,
          "date": "1990年2月23日（平成2年）",
          "_date_raw": "1990/02/23"
        },
        {
          "rank": 7,
          "value": 45,
          "date": "1990年2月11日（平成2年）",
          "_date_raw": "1990/02/11"
        },
        {
          "rank": 8,
          "value": 44,
          "date": "2004年2月22日（平成16年）",
          "_date_raw": "2004/02/22"
        },
        {
          "rank": 9,
          "value": 42,
          "date": "2013年2月18日（平成25年）",
          "_date_raw": "2013/02/18"
        },
        {
          "rank": 10,
          "value": 40,
          "date": "2006年2月26日（平成18年）",
          "_date_raw": "2006/02/26"
        }
      ]
    },
    {
      "stationName": "彦根",
      "startDate": "1894年2月（明治27年）",
      "ranks": [
        {
          "rank": 1,
          "value": 57.4,
          "date": "1922年2月16日（大正11年）",
          "_date_raw": "1922/02/16"
        },
        {
          "rank": 2,
          "value": 53.5,
          "date": "1979年2月23日（昭和54年）",
          "_date_raw": "1979/02/23"
        },
        {
          "rank": 3,
          "value": 53,
          "date": "2011年2月28日（平成23年）",
          "_date_raw": "2011/02/28"
        },
        {
          "rank": 4,
          "value": 47,
          "date": "1976年2月29日（昭和51年）",
          "_date_raw": "1976/02/29"
        },
        {
          "rank": 5,
          "value": 44,
          "date": "2020年2月16日（令和2年）",
          "_date_raw": "2020/02/16"
        },
        {
          "rank": 6,
          "value": 42.1,
          "date": "1906年2月1日（明治39年）",
          "_date_raw": "1906/02/01"
        },
        {
          "rank": 7,
          "value": 40.5,
          "date": "1985年2月9日（昭和60年）",
          "_date_raw": "1985/02/09"
        },
        {
          "rank": 8,
          "value": 39,
          "date": "1994年2月3日（平成6年）",
          "_date_raw": "1994/02/03"
        },
        {
          "rank": 9,
          "value": 39,
          "date": "1976年2月28日（昭和51年）",
          "_date_raw": "1976/02/28"
        },
        {
          "rank": 10,
          "value": 38.5,
          "date": "2021年2月15日（令和3年）",
          "_date_raw": "2021/02/15"
        }
      ]
    },
    {
      "stationName": "近江八幡",
      "startDate": "1977年2月（昭和52年）",
      "ranks": [
        {
          "rank": 1,
          "value": 47,
          "date": "1979年2月23日（昭和54年）",
          "_date_raw": "1979/02/23"
        },
        {
          "rank": 2,
          "value": 45,
          "date": "2011年2月28日（平成23年）",
          "_date_raw": "2011/02/28"
        },
        {
          "rank": 3,
          "value": 42,
          "date": "1990年2月23日（平成2年）",
          "_date_raw": "1990/02/23"
        },
        {
          "rank": 4,
          "value": 39.5,
          "date": "2013年2月18日（平成25年）",
          "_date_raw": "2013/02/18"
        },
        {
          "rank": 5,
          "value": 38,
          "date": "1998年2月20日（平成10年）",
          "_date_raw": "1998/02/20"
        },
        {
          "rank": 6,
          "value": 37,
          "date": "2021年2月15日（令和3年）",
          "_date_raw": "2021/02/15"
        },
        {
          "rank": 7,
          "value": 37,
          "date": "2020年2月16日（令和2年）",
          "_date_raw": "2020/02/16"
        },
        {
          "rank": 8,
          "value": 35,
          "date": "1990年2月11日（平成2年）",
          "_date_raw": "1990/02/11"
        },
        {
          "rank": 9,
          "value": 35,
          "date": "1985年2月9日（昭和60年）",
          "_date_raw": "1985/02/09"
        },
        {
          "rank": 10,
          "value": 33,
          "date": "2006年2月1日（平成18年）",
          "_date_raw": "2006/02/01"
        }
      ]
    },
    {
      "stationName": "東近江",
      "startDate": "1976年2月（昭和51年）",
      "ranks": [
        {
          "rank": 1,
          "value": 42.5,
          "date": "2011年2月28日（平成23年）",
          "_date_raw": "2011/02/28"
        },
        {
          "rank": 2,
          "value": 40,
          "date": "2013年2月18日（平成25年）",
          "_date_raw": "2013/02/18"
        },
        {
          "rank": 3,
          "value": 40,
          "date": "1979年2月23日（昭和54年）",
          "_date_raw": "1979/02/23"
        },
        {
          "rank": 4,
          "value": 37,
          "date": "1998年2月20日（平成10年）",
          "_date_raw": "1998/02/20"
        },
        {
          "rank": 5,
          "value": 35,
          "date": "2021年2月15日（令和3年）",
          "_date_raw": "2021/02/15"
        },
        {
          "rank": 6,
          "value": 35,
          "date": "1990年2月11日（平成2年）",
          "_date_raw": "1990/02/11"
        },
        {
          "rank": 7,
          "value": 33.5,
          "date": "2012年2月7日（平成24年）",
          "_date_raw": "2012/02/07"
        },
        {
          "rank": 8,
          "value": 33,
          "date": "1990年2月23日（平成2年）",
          "_date_raw": "1990/02/23"
        },
        {
          "rank": 9,
          "value": 31,
          "date": "2006年2月1日（平成18年）",
          "_date_raw": "2006/02/01"
        },
        {
          "rank": 10,
          "value": 31,
          "date": "1989年2月17日（平成元年）",
          "_date_raw": "1989/02/17"
        }
      ]
    },
    {
      "stationName": "大津",
      "startDate": "1978年2月（昭和53年）",
      "ranks": [
        {
          "rank": 1,
          "value": 50,
          "date": "1990年2月23日（平成2年）",
          "_date_raw": "1990/02/23"
        },
        {
          "rank": 2,
          "value": 47.5,
          "date": "2013年2月18日（平成25年）",
          "_date_raw": "2013/02/18"
        },
        {
          "rank": 3,
          "value": 46,
          "date": "1989年2月25日（平成元年）",
          "_date_raw": "1989/02/25"
        },
        {
          "rank": 4,
          "value": 44,
          "date": "1979年2月23日（昭和54年）",
          "_date_raw": "1979/02/23"
        },
        {
          "rank": 5,
          "value": 42.5,
          "date": "2011年2月28日（平成23年）",
          "_date_raw": "2011/02/28"
        },
        {
          "rank": 6,
          "value": 42,
          "date": "1990年2月11日（平成2年）",
          "_date_raw": "1990/02/11"
        },
        {
          "rank": 7,
          "value": 35,
          "date": "2012年2月7日（平成24年）",
          "_date_raw": "2012/02/07"
        },
        {
          "rank": 8,
          "value": 35,
          "date": "2006年2月1日（平成18年）",
          "_date_raw": "2006/02/01"
        },
        {
          "rank": 9,
          "value": 34.5,
          "date": "2021年2月15日（令和3年）",
          "_date_raw": "2021/02/15"
        },
        {
          "rank": 10,
          "value": 33,
          "date": "2010年2月26日（平成22年）",
          "_date_raw": "2010/02/26"
        }
      ]
    },
    {
      "stationName": "信楽",
      "startDate": "1979年2月（昭和54年）",
      "ranks": [
        {
          "rank": 1,
          "value": 49,
          "date": "2011年2月28日（平成23年）",
          "_date_raw": "2011/02/28"
        },
        {
          "rank": 2,
          "value": 44,
          "date": "1998年2月20日（平成10年）",
          "_date_raw": "1998/02/20"
        },
        {
          "rank": 3,
          "value": 42,
          "date": "1989年2月17日（平成元年）",
          "_date_raw": "1989/02/17"
        },
        {
          "rank": 4,
          "value": 40,
          "date": "1990年2月11日（平成2年）",
          "_date_raw": "1990/02/11"
        },
        {
          "rank": 5,
          "value": 40,
          "date": "1979年2月23日（昭和54年）",
          "_date_raw": "1979/02/23"
        },
        {
          "rank": 6,
          "value": 39.5,
          "date": "2013年2月18日（平成25年）",
          "_date_raw": "2013/02/18"
        },
        {
          "rank": 7,
          "value": 35,
          "date": "2021年2月15日（令和3年）",
          "_date_raw": "2021/02/15"
        },
        {
          "rank": 8,
          "value": 33,
          "date": "2012年2月7日（平成24年）",
          "_date_raw": "2012/02/07"
        },
        {
          "rank": 9,
          "value": 32,
          "date": "1989年2月25日（平成元年）",
          "_date_raw": "1989/02/25"
        },
        {
          "rank": 10,
          "value": 32,
          "date": "1985年2月9日（昭和60年）",
          "_date_raw": "1985/02/09"
        }
      ]
    },
    {
      "stationName": "土山",
      "startDate": "1979年2月（昭和54年）",
      "ranks": [
        {
          "rank": 1,
          "value": 70,
          "date": "1998年2月20日（平成10年）",
          "_date_raw": "1998/02/20"
        },
        {
          "rank": 2,
          "value": 49,
          "date": "2011年2月28日（平成23年）",
          "_date_raw": "2011/02/28"
        },
        {
          "rank": 3,
          "value": 45,
          "date": "1994年2月21日（平成6年）",
          "_date_raw": "1994/02/21"
        },
        {
          "rank": 4,
          "value": 41,
          "date": "1989年2月17日（平成元年）",
          "_date_raw": "1989/02/17"
        },
        {
          "rank": 5,
          "value": 37,
          "date": "1993年2月2日（平成5年）",
          "_date_raw": "1993/02/02"
        },
        {
          "rank": 6,
          "value": 36.5,
          "date": "2021年2月15日（令和3年）",
          "_date_raw": "2021/02/15"
        },
        {
          "rank": 7,
          "value": 34,
          "date": "2006年2月26日（平成18年）",
          "_date_raw": "2006/02/26"
        },
        {
          "rank": 8,
          "value": 34,
          "date": "1979年2月23日（昭和54年）",
          "_date_raw": "1979/02/23"
        },
        {
          "rank": 9,
          "value": 31,
          "date": "2012年2月7日（平成24年）",
          "_date_raw": "2012/02/07"
        },
        {
          "rank": 10,
          "value": 29.5,
          "date": "2013年2月18日（平成25年）",
          "_date_raw": "2013/02/18"
        }
      ]
    }
  ]
}
