{
  "updatedAt": "2026-03-31T21:30:00+09:00",
  "prefecture": "大阪府",
  "element": "monthPrecipHigh",
  "month": "2",
  "rows": [
    {
      "stationName": "大阪",
      "startDate": "1883年2月（明治16年）",
      "ranks": [
        {
          "rank": 1,
          "value": 195.5,
          "date": "1989年2月（平成元年）",
          "highlightLive": false,
          "highlightWithinYear": false
        },
        {
          "rank": 2,
          "value": 160.1,
          "date": "1922年2月（大正11年）",
          "highlightLive": false,
          "highlightWithinYear": false
        },
        {
          "rank": 3,
          "value": 149.3,
          "date": "1912年2月（明治45年）",
          "highlightLive": false,
          "highlightWithinYear": false
        },
        {
          "rank": 4,
          "value": 147.5,
          "date": "1990年2月（平成2年）",
          "highlightLive": false,
          "highlightWithinYear": false
        },
        {
          "rank": 5,
          "value": 142.1,
          "date": "1959年2月（昭和34年）",
          "highlightLive": false,
          "highlightWithinYear": false
        },
        {
          "rank": 6,
          "value": 132,
          "date": "2010年2月（平成22年）",
          "highlightLive": false,
          "highlightWithinYear": false
        },
        {
          "rank": 7,
          "value": 122,
          "date": "1915年2月（大正4年）",
          "highlightLive": false,
          "highlightWithinYear": false
        },
        {
          "rank": 8,
          "value": 115,
          "date": "1976年2月（昭和51年）",
          "highlightLive": false,
          "highlightWithinYear": false
        },
        {
          "rank": 9,
          "value": 113.5,
          "date": "2011年2月（平成23年）",
          "highlightLive": false,
          "highlightWithinYear": false
        },
        {
          "rank": 10,
          "value": 110.5,
          "date": "1931年2月（昭和6年）",
          "highlightLive": false,
          "highlightWithinYear": false
        }
      ]
    }
  ]
}