{
  "updatedAt": "2026-04-28T03:14:20.610944+09:00",
  "observedLatestAt": "2026-04-28T03:00:00+09:00",
  "prefecture": "山形県",
  "region": "東北",
  "element": "monthAvgTempLow",
  "month": "8",
  "rows": [
    {
      "stationName": "飛島",
      "startDate": "1979年8月（昭和54年）",
      "ranks": [
        {
          "rank": 1,
          "value": 21.2,
          "date": "1993年8月（平成5年）",
          "_date_raw": "1993/08/01"
        },
        {
          "rank": 2,
          "value": 22.2,
          "date": "2003年8月（平成15年）",
          "_date_raw": "2003/08/01"
        },
        {
          "rank": 3,
          "value": 22.6,
          "date": "1980年8月（昭和55年）",
          "_date_raw": "1980/08/01"
        },
        {
          "rank": 4,
          "value": 22.7,
          "date": "2009年8月（平成21年）",
          "_date_raw": "2009/08/01"
        },
        {
          "rank": 5,
          "value": 22.8,
          "date": "1991年8月（平成3年）",
          "_date_raw": "1991/08/01"
        },
        {
          "rank": 6,
          "value": 23.2,
          "date": "1998年8月（平成10年）",
          "_date_raw": "1998/08/01"
        },
        {
          "rank": 7,
          "value": 23.4,
          "date": "2008年8月（平成20年）",
          "_date_raw": "2008/08/01"
        },
        {
          "rank": 8,
          "value": 23.5,
          "date": "1996年8月（平成8年）",
          "_date_raw": "1996/08/01"
        },
        {
          "rank": 9,
          "value": 23.5,
          "date": "1981年8月（昭和56年）",
          "_date_raw": "1981/08/01"
        },
        {
          "rank": 10,
          "value": 23.7,
          "date": "2002年8月（平成14年）",
          "_date_raw": "2002/08/01"
        }
      ]
    },
    {
      "stationName": "酒田",
      "startDate": "1937年8月（昭和12年）",
      "ranks": [
        {
          "rank": 1,
          "value": 21.8,
          "date": "1976年8月（昭和51年）",
          "_date_raw": "1976/08/01"
        },
        {
          "rank": 2,
          "value": 22,
          "date": "1980年8月（昭和55年）",
          "_date_raw": "1980/08/01"
        },
        {
          "rank": 3,
          "value": 22.3,
          "date": "1993年8月（平成5年）",
          "_date_raw": "1993/08/01"
        },
        {
          "rank": 4,
          "value": 22.7,
          "date": "1956年8月（昭和31年）",
          "_date_raw": "1956/08/01"
        },
        {
          "rank": 5,
          "value": 23.1,
          "date": "1977年8月（昭和52年）",
          "_date_raw": "1977/08/01"
        },
        {
          "rank": 6,
          "value": 23.2,
          "date": "1953年8月（昭和28年）",
          "_date_raw": "1953/08/01"
        },
        {
          "rank": 7,
          "value": 23.4,
          "date": "1941年8月（昭和16年）",
          "_date_raw": "1941/08/01"
        },
        {
          "rank": 8,
          "value": 23.5,
          "date": "1981年8月（昭和56年）",
          "_date_raw": "1981/08/01"
        },
        {
          "rank": 9,
          "value": 23.5,
          "date": "1958年8月（昭和33年）",
          "_date_raw": "1958/08/01"
        },
        {
          "rank": 10,
          "value": 23.5,
          "date": "1940年8月（昭和15年）",
          "_date_raw": "1940/08/01"
        }
      ]
    },
    {
      "stationName": "差首鍋",
      "startDate": "1977年8月（昭和52年）",
      "ranks": [
        {
          "rank": 1,
          "value": 20.2,
          "date": "1993年8月（平成5年）",
          "_date_raw": "1993/08/01"
        },
        {
          "rank": 2,
          "value": 20.3,
          "date": "1980年8月（昭和55年）",
          "_date_raw": "1980/08/01"
        },
        {
          "rank": 3,
          "value": 21.4,
          "date": "1977年8月（昭和52年）",
          "_date_raw": "1977/08/01"
        },
        {
          "rank": 4,
          "value": 21.7,
          "date": "2003年8月（平成15年）",
          "_date_raw": "2003/08/01"
        },
        {
          "rank": 5,
          "value": 21.7,
          "date": "1991年8月（平成3年）",
          "_date_raw": "1991/08/01"
        },
        {
          "rank": 6,
          "value": 21.8,
          "date": "1996年8月（平成8年）",
          "_date_raw": "1996/08/01"
        },
        {
          "rank": 7,
          "value": 22,
          "date": "1998年8月（平成10年）",
          "_date_raw": "1998/08/01"
        },
        {
          "rank": 8,
          "value": 22.2,
          "date": "2008年8月（平成20年）",
          "_date_raw": "2008/08/01"
        },
        {
          "rank": 9,
          "value": 22.3,
          "date": "2004年8月（平成16年）",
          "_date_raw": "2004/08/01"
        },
        {
          "rank": 10,
          "value": 22.3,
          "date": "1997年8月（平成9年）",
          "_date_raw": "1997/08/01"
        }
      ]
    },
    {
      "stationName": "金山",
      "startDate": "1977年8月（昭和52年）",
      "ranks": [
        {
          "rank": 1,
          "value": 20.2,
          "date": "1993年8月（平成5年）",
          "_date_raw": "1993/08/01"
        },
        {
          "rank": 2,
          "value": 20.2,
          "date": "1980年8月（昭和55年）",
          "_date_raw": "1980/08/01"
        },
        {
          "rank": 3,
          "value": 21.5,
          "date": "1977年8月（昭和52年）",
          "_date_raw": "1977/08/01"
        },
        {
          "rank": 4,
          "value": 21.7,
          "date": "2003年8月（平成15年）",
          "_date_raw": "2003/08/01"
        },
        {
          "rank": 5,
          "value": 21.7,
          "date": "1991年8月（平成3年）",
          "_date_raw": "1991/08/01"
        },
        {
          "rank": 6,
          "value": 21.8,
          "date": "1981年8月（昭和56年）",
          "_date_raw": "1981/08/01"
        },
        {
          "rank": 7,
          "value": 22,
          "date": "1996年8月（平成8年）",
          "_date_raw": "1996/08/01"
        },
        {
          "rank": 8,
          "value": 22.1,
          "date": "2009年8月（平成21年）",
          "_date_raw": "2009/08/01"
        },
        {
          "rank": 9,
          "value": 22.1,
          "date": "1998年8月（平成10年）",
          "_date_raw": "1998/08/01"
        },
        {
          "rank": 10,
          "value": 22.2,
          "date": "1987年8月（昭和62年）",
          "_date_raw": "1987/08/01"
        }
      ]
    },
    {
      "stationName": "鶴岡",
      "startDate": "1977年8月（昭和52年）",
      "ranks": [
        {
          "rank": 1,
          "value": 21.9,
          "date": "1993年8月（平成5年）",
          "_date_raw": "1993/08/01"
        },
        {
          "rank": 2,
          "value": 22.1,
          "date": "1980年8月（昭和55年）",
          "_date_raw": "1980/08/01"
        },
        {
          "rank": 3,
          "value": 23,
          "date": "1977年8月（昭和52年）",
          "_date_raw": "1977/08/01"
        },
        {
          "rank": 4,
          "value": 23.3,
          "date": "2003年8月（平成15年）",
          "_date_raw": "2003/08/01"
        },
        {
          "rank": 5,
          "value": 23.4,
          "date": "1991年8月（平成3年）",
          "_date_raw": "1991/08/01"
        },
        {
          "rank": 6,
          "value": 23.8,
          "date": "1981年8月（昭和56年）",
          "_date_raw": "1981/08/01"
        },
        {
          "rank": 7,
          "value": 23.9,
          "date": "2009年8月（平成21年）",
          "_date_raw": "2009/08/01"
        },
        {
          "rank": 8,
          "value": 23.9,
          "date": "1998年8月（平成10年）",
          "_date_raw": "1998/08/01"
        },
        {
          "rank": 9,
          "value": 24,
          "date": "1996年8月（平成8年）",
          "_date_raw": "1996/08/01"
        },
        {
          "rank": 10,
          "value": 24.1,
          "date": "2008年8月（平成20年）",
          "_date_raw": "2008/08/01"
        }
      ]
    },
    {
      "stationName": "狩川",
      "startDate": "1977年8月（昭和52年）",
      "ranks": [
        {
          "rank": 1,
          "value": 21.4,
          "date": "1993年8月（平成5年）",
          "_date_raw": "1993/08/01"
        },
        {
          "rank": 2,
          "value": 21.6,
          "date": "1980年8月（昭和55年）",
          "_date_raw": "1980/08/01"
        },
        {
          "rank": 3,
          "value": 22.6,
          "date": "1977年8月（昭和52年）",
          "_date_raw": "1977/08/01"
        },
        {
          "rank": 4,
          "value": 22.7,
          "date": "2003年8月（平成15年）",
          "_date_raw": "2003/08/01"
        },
        {
          "rank": 5,
          "value": 22.9,
          "date": "1981年8月（昭和56年）",
          "_date_raw": "1981/08/01"
        },
        {
          "rank": 6,
          "value": 23,
          "date": "2009年8月（平成21年）",
          "_date_raw": "2009/08/01"
        },
        {
          "rank": 7,
          "value": 23,
          "date": "1991年8月（平成3年）",
          "_date_raw": "1991/08/01"
        },
        {
          "rank": 8,
          "value": 23.3,
          "date": "1998年8月（平成10年）",
          "_date_raw": "1998/08/01"
        },
        {
          "rank": 9,
          "value": 23.5,
          "date": "2008年8月（平成20年）",
          "_date_raw": "2008/08/01"
        },
        {
          "rank": 10,
          "value": 23.5,
          "date": "1996年8月（平成8年）",
          "_date_raw": "1996/08/01"
        }
      ]
    },
    {
      "stationName": "新庄",
      "startDate": "1958年8月（昭和33年）",
      "ranks": [
        {
          "rank": 1,
          "value": 20.6,
          "date": "1976年8月（昭和51年）",
          "_date_raw": "1976/08/01"
        },
        {
          "rank": 2,
          "value": 20.8,
          "date": "1980年8月（昭和55年）",
          "_date_raw": "1980/08/01"
        },
        {
          "rank": 3,
          "value": 21.1,
          "date": "1993年8月（平成5年）",
          "_date_raw": "1993/08/01"
        },
        {
          "rank": 4,
          "value": 22,
          "date": "1977年8月（昭和52年）",
          "_date_raw": "1977/08/01"
        },
        {
          "rank": 5,
          "value": 22.3,
          "date": "2003年8月（平成15年）",
          "_date_raw": "2003/08/01"
        },
        {
          "rank": 6,
          "value": 22.4,
          "date": "1981年8月（昭和56年）",
          "_date_raw": "1981/08/01"
        },
        {
          "rank": 7,
          "value": 22.5,
          "date": "1991年8月（平成3年）",
          "_date_raw": "1991/08/01"
        },
        {
          "rank": 8,
          "value": 22.6,
          "date": "1958年8月（昭和33年）",
          "_date_raw": "1958/08/01"
        },
        {
          "rank": 9,
          "value": 22.7,
          "date": "1998年8月（平成10年）",
          "_date_raw": "1998/08/01"
        },
        {
          "rank": 10,
          "value": 22.7,
          "date": "1969年8月（昭和44年）",
          "_date_raw": "1969/08/01"
        }
      ]
    },
    {
      "stationName": "向町",
      "startDate": "1977年8月（昭和52年）",
      "ranks": [
        {
          "rank": 1,
          "value": 19.5,
          "date": "1980年8月（昭和55年）",
          "_date_raw": "1980/08/01"
        },
        {
          "rank": 2,
          "value": 20.2,
          "date": "1993年8月（平成5年）",
          "_date_raw": "1993/08/01"
        },
        {
          "rank": 3,
          "value": 21.2,
          "date": "1977年8月（昭和52年）",
          "_date_raw": "1977/08/01"
        },
        {
          "rank": 4,
          "value": 21.6,
          "date": "1991年8月（平成3年）",
          "_date_raw": "1991/08/01"
        },
        {
          "rank": 5,
          "value": 21.8,
          "date": "2003年8月（平成15年）",
          "_date_raw": "2003/08/01"
        },
        {
          "rank": 6,
          "value": 21.8,
          "date": "2001年8月（平成13年）",
          "_date_raw": "2001/08/01"
        },
        {
          "rank": 7,
          "value": 22,
          "date": "2009年8月（平成21年）",
          "_date_raw": "2009/08/01"
        },
        {
          "rank": 8,
          "value": 22,
          "date": "1981年8月（昭和56年）",
          "_date_raw": "1981/08/01"
        },
        {
          "rank": 9,
          "value": 22.1,
          "date": "1998年8月（平成10年）",
          "_date_raw": "1998/08/01"
        },
        {
          "rank": 10,
          "value": 22.1,
          "date": "1996年8月（平成8年）",
          "_date_raw": "1996/08/01"
        }
      ]
    },
    {
      "stationName": "肘折",
      "startDate": "1977年8月（昭和52年）",
      "ranks": [
        {
          "rank": 1,
          "value": 18.7,
          "date": "1980年8月（昭和55年）",
          "_date_raw": "1980/08/01"
        },
        {
          "rank": 2,
          "value": 19.5,
          "date": "1993年8月（平成5年）",
          "_date_raw": "1993/08/01"
        },
        {
          "rank": 3,
          "value": 20.1,
          "date": "1977年8月（昭和52年）",
          "_date_raw": "1977/08/01"
        },
        {
          "rank": 4,
          "value": 20.4,
          "date": "1996年8月（平成8年）",
          "_date_raw": "1996/08/01"
        },
        {
          "rank": 5,
          "value": 20.5,
          "date": "1981年8月（昭和56年）",
          "_date_raw": "1981/08/01"
        },
        {
          "rank": 6,
          "value": 20.7,
          "date": "2009年8月（平成21年）",
          "_date_raw": "2009/08/01"
        },
        {
          "rank": 7,
          "value": 20.7,
          "date": "2003年8月（平成15年）",
          "_date_raw": "2003/08/01"
        },
        {
          "rank": 8,
          "value": 20.8,
          "date": "1991年8月（平成3年）",
          "_date_raw": "1991/08/01"
        },
        {
          "rank": 9,
          "value": 20.9,
          "date": "2008年8月（平成20年）",
          "_date_raw": "2008/08/01"
        },
        {
          "rank": 10,
          "value": 20.9,
          "date": "2004年8月（平成16年）",
          "_date_raw": "2004/08/01"
        }
      ]
    },
    {
      "stationName": "尾花沢",
      "startDate": "1976年8月（昭和51年）",
      "ranks": [
        {
          "rank": 1,
          "value": 20.1,
          "date": "1980年8月（昭和55年）",
          "_date_raw": "1980/08/01"
        },
        {
          "rank": 2,
          "value": 20.4,
          "date": "1976年8月（昭和51年）",
          "_date_raw": "1976/08/01"
        },
        {
          "rank": 3,
          "value": 20.5,
          "date": "1993年8月（平成5年）",
          "_date_raw": "1993/08/01"
        },
        {
          "rank": 4,
          "value": 21.7,
          "date": "1977年8月（昭和52年）",
          "_date_raw": "1977/08/01"
        },
        {
          "rank": 5,
          "value": 21.8,
          "date": "1991年8月（平成3年）",
          "_date_raw": "1991/08/01"
        },
        {
          "rank": 6,
          "value": 22.2,
          "date": "2003年8月（平成15年）",
          "_date_raw": "2003/08/01"
        },
        {
          "rank": 7,
          "value": 22.3,
          "date": "2001年8月（平成13年）",
          "_date_raw": "2001/08/01"
        },
        {
          "rank": 8,
          "value": 22.3,
          "date": "1996年8月（平成8年）",
          "_date_raw": "1996/08/01"
        },
        {
          "rank": 9,
          "value": 22.3,
          "date": "1987年8月（昭和62年）",
          "_date_raw": "1987/08/01"
        },
        {
          "rank": 10,
          "value": 22.4,
          "date": "1997年8月（平成9年）",
          "_date_raw": "1997/08/01"
        }
      ]
    },
    {
      "stationName": "村山",
      "startDate": "2002年8月（平成14年）",
      "ranks": [
        {
          "rank": 1,
          "value": 22.7,
          "date": "2003年8月（平成15年）",
          "_date_raw": "2003/08/01"
        },
        {
          "rank": 2,
          "value": 23,
          "date": "2009年8月（平成21年）",
          "_date_raw": "2009/08/01"
        },
        {
          "rank": 3,
          "value": 23.2,
          "date": "2008年8月（平成20年）",
          "_date_raw": "2008/08/01"
        },
        {
          "rank": 4,
          "value": 23.3,
          "date": "2004年8月（平成16年）",
          "_date_raw": "2004/08/01"
        },
        {
          "rank": 5,
          "value": 23.4,
          "date": "2017年8月（平成29年）",
          "_date_raw": "2017/08/01"
        },
        {
          "rank": 6,
          "value": 23.6,
          "date": "2015年8月（平成27年）",
          "_date_raw": "2015/08/01"
        },
        {
          "rank": 7,
          "value": 24,
          "date": "2018年8月（平成30年）",
          "_date_raw": "2018/08/01"
        },
        {
          "rank": 8,
          "value": 24.1,
          "date": "2022年8月（令和4年）",
          "_date_raw": "2022/08/01"
        },
        {
          "rank": 9,
          "value": 24.2,
          "date": "2014年8月（平成26年）",
          "_date_raw": "2014/08/01"
        },
        {
          "rank": 10,
          "value": 24.3,
          "date": "2002年8月（平成14年）",
          "_date_raw": "2002/08/01"
        }
      ]
    },
    {
      "stationName": "大井沢",
      "startDate": "1979年8月（昭和54年）",
      "ranks": [
        {
          "rank": 1,
          "value": 18.8,
          "date": "1980年8月（昭和55年）",
          "_date_raw": "1980/08/01"
        },
        {
          "rank": 2,
          "value": 19.1,
          "date": "1993年8月（平成5年）",
          "_date_raw": "1993/08/01"
        },
        {
          "rank": 3,
          "value": 19.9,
          "date": "1981年8月（昭和56年）",
          "_date_raw": "1981/08/01"
        },
        {
          "rank": 4,
          "value": 20.1,
          "date": "2003年8月（平成15年）",
          "_date_raw": "2003/08/01"
        },
        {
          "rank": 5,
          "value": 20.4,
          "date": "1996年8月（平成8年）",
          "_date_raw": "1996/08/01"
        },
        {
          "rank": 6,
          "value": 20.5,
          "date": "1991年8月（平成3年）",
          "_date_raw": "1991/08/01"
        },
        {
          "rank": 7,
          "value": 20.8,
          "date": "2015年8月（平成27年）",
          "_date_raw": "2015/08/01"
        },
        {
          "rank": 8,
          "value": 20.8,
          "date": "2004年8月（平成16年）",
          "_date_raw": "2004/08/01"
        },
        {
          "rank": 9,
          "value": 21,
          "date": "2009年8月（平成21年）",
          "_date_raw": "2009/08/01"
        },
        {
          "rank": 10,
          "value": 21,
          "date": "2001年8月（平成13年）",
          "_date_raw": "2001/08/01"
        }
      ]
    },
    {
      "stationName": "左沢",
      "startDate": "1977年8月（昭和52年）",
      "ranks": [
        {
          "rank": 1,
          "value": 20.4,
          "date": "1980年8月（昭和55年）",
          "_date_raw": "1980/08/01"
        },
        {
          "rank": 2,
          "value": 21,
          "date": "1993年8月（平成5年）",
          "_date_raw": "1993/08/01"
        },
        {
          "rank": 3,
          "value": 22.1,
          "date": "1977年8月（昭和52年）",
          "_date_raw": "1977/08/01"
        },
        {
          "rank": 4,
          "value": 22.3,
          "date": "2009年8月（平成21年）",
          "_date_raw": "2009/08/01"
        },
        {
          "rank": 5,
          "value": 22.3,
          "date": "1991年8月（平成3年）",
          "_date_raw": "1991/08/01"
        },
        {
          "rank": 6,
          "value": 22.3,
          "date": "1981年8月（昭和56年）",
          "_date_raw": "1981/08/01"
        },
        {
          "rank": 7,
          "value": 22.4,
          "date": "2003年8月（平成15年）",
          "_date_raw": "2003/08/01"
        },
        {
          "rank": 8,
          "value": 22.5,
          "date": "2008年8月（平成20年）",
          "_date_raw": "2008/08/01"
        },
        {
          "rank": 9,
          "value": 22.6,
          "date": "1996年8月（平成8年）",
          "_date_raw": "1996/08/01"
        },
        {
          "rank": 10,
          "value": 22.7,
          "date": "2017年8月（平成29年）",
          "_date_raw": "2017/08/01"
        }
      ]
    },
    {
      "stationName": "山形",
      "startDate": "1889年8月（明治22年）",
      "ranks": [
        {
          "rank": 1,
          "value": 20.3,
          "date": "1905年8月（明治38年）",
          "_date_raw": "1905/08/01"
        },
        {
          "rank": 2,
          "value": 21.3,
          "date": "1980年8月（昭和55年）",
          "_date_raw": "1980/08/01"
        },
        {
          "rank": 3,
          "value": 21.3,
          "date": "1913年8月（大正2年）",
          "_date_raw": "1913/08/01"
        },
        {
          "rank": 4,
          "value": 21.5,
          "date": "1976年8月（昭和51年）",
          "_date_raw": "1976/08/01"
        },
        {
          "rank": 5,
          "value": 21.6,
          "date": "1902年8月（明治35年）",
          "_date_raw": "1902/08/01"
        },
        {
          "rank": 6,
          "value": 21.9,
          "date": "1993年8月（平成5年）",
          "_date_raw": "1993/08/01"
        },
        {
          "rank": 7,
          "value": 22.3,
          "date": "1910年8月（明治43年）",
          "_date_raw": "1910/08/01"
        },
        {
          "rank": 8,
          "value": 22.4,
          "date": "1953年8月（昭和28年）",
          "_date_raw": "1953/08/01"
        },
        {
          "rank": 9,
          "value": 22.4,
          "date": "1934年8月（昭和9年）",
          "_date_raw": "1934/08/01"
        },
        {
          "rank": 10,
          "value": 22.6,
          "date": "1956年8月（昭和31年）",
          "_date_raw": "1956/08/01"
        }
      ]
    },
    {
      "stationName": "長井",
      "startDate": "1977年8月（昭和52年）",
      "ranks": [
        {
          "rank": 1,
          "value": 20.8,
          "date": "1993年8月（平成5年）",
          "_date_raw": "1993/08/01"
        },
        {
          "rank": 2,
          "value": 20.9,
          "date": "1980年8月（昭和55年）",
          "_date_raw": "1980/08/01"
        },
        {
          "rank": 3,
          "value": 22,
          "date": "1991年8月（平成3年）",
          "_date_raw": "1991/08/01"
        },
        {
          "rank": 4,
          "value": 22.2,
          "date": "1996年8月（平成8年）",
          "_date_raw": "1996/08/01"
        },
        {
          "rank": 5,
          "value": 22.4,
          "date": "2003年8月（平成15年）",
          "_date_raw": "2003/08/01"
        },
        {
          "rank": 6,
          "value": 22.5,
          "date": "1981年8月（昭和56年）",
          "_date_raw": "1981/08/01"
        },
        {
          "rank": 7,
          "value": 22.6,
          "date": "2001年8月（平成13年）",
          "_date_raw": "2001/08/01"
        },
        {
          "rank": 8,
          "value": 22.7,
          "date": "2008年8月（平成20年）",
          "_date_raw": "2008/08/01"
        },
        {
          "rank": 9,
          "value": 22.7,
          "date": "1998年8月（平成10年）",
          "_date_raw": "1998/08/01"
        },
        {
          "rank": 10,
          "value": 22.8,
          "date": "2009年8月（平成21年）",
          "_date_raw": "2009/08/01"
        }
      ]
    },
    {
      "stationName": "小国",
      "startDate": "1977年8月（昭和52年）",
      "ranks": [
        {
          "rank": 1,
          "value": 21.2,
          "date": "1993年8月（平成5年）",
          "_date_raw": "1993/08/01"
        },
        {
          "rank": 2,
          "value": 21.2,
          "date": "1980年8月（昭和55年）",
          "_date_raw": "1980/08/01"
        },
        {
          "rank": 3,
          "value": 22.2,
          "date": "1977年8月（昭和52年）",
          "_date_raw": "1977/08/01"
        },
        {
          "rank": 4,
          "value": 22.4,
          "date": "2009年8月（平成21年）",
          "_date_raw": "2009/08/01"
        },
        {
          "rank": 5,
          "value": 22.5,
          "date": "1991年8月（平成3年）",
          "_date_raw": "1991/08/01"
        },
        {
          "rank": 6,
          "value": 22.6,
          "date": "2003年8月（平成15年）",
          "_date_raw": "2003/08/01"
        },
        {
          "rank": 7,
          "value": 22.6,
          "date": "1981年8月（昭和56年）",
          "_date_raw": "1981/08/01"
        },
        {
          "rank": 8,
          "value": 22.7,
          "date": "2004年8月（平成16年）",
          "_date_raw": "2004/08/01"
        },
        {
          "rank": 9,
          "value": 22.7,
          "date": "1996年8月（平成8年）",
          "_date_raw": "1996/08/01"
        },
        {
          "rank": 10,
          "value": 22.8,
          "date": "2008年8月（平成20年）",
          "_date_raw": "2008/08/01"
        }
      ]
    },
    {
      "stationName": "高畠",
      "startDate": "1977年8月（昭和52年）",
      "ranks": [
        {
          "rank": 1,
          "value": 20.5,
          "date": "1980年8月（昭和55年）",
          "_date_raw": "1980/08/01"
        },
        {
          "rank": 2,
          "value": 21.3,
          "date": "1993年8月（平成5年）",
          "_date_raw": "1993/08/01"
        },
        {
          "rank": 3,
          "value": 22.3,
          "date": "1977年8月（昭和52年）",
          "_date_raw": "1977/08/01"
        },
        {
          "rank": 4,
          "value": 22.5,
          "date": "1991年8月（平成3年）",
          "_date_raw": "1991/08/01"
        },
        {
          "rank": 5,
          "value": 22.7,
          "date": "2003年8月（平成15年）",
          "_date_raw": "2003/08/01"
        },
        {
          "rank": 6,
          "value": 22.9,
          "date": "2009年8月（平成21年）",
          "_date_raw": "2009/08/01"
        },
        {
          "rank": 7,
          "value": 22.9,
          "date": "1981年8月（昭和56年）",
          "_date_raw": "1981/08/01"
        },
        {
          "rank": 8,
          "value": 23,
          "date": "1998年8月（平成10年）",
          "_date_raw": "1998/08/01"
        },
        {
          "rank": 9,
          "value": 23.1,
          "date": "2004年8月（平成16年）",
          "_date_raw": "2004/08/01"
        },
        {
          "rank": 10,
          "value": 23.1,
          "date": "1996年8月（平成8年）",
          "_date_raw": "1996/08/01"
        }
      ]
    },
    {
      "stationName": "中津川",
      "startDate": "1977年8月（昭和52年）",
      "ranks": [
        {
          "rank": 1,
          "value": 19.8,
          "date": "1980年8月（昭和55年）",
          "_date_raw": "1980/08/01"
        },
        {
          "rank": 2,
          "value": 20.4,
          "date": "1993年8月（平成5年）",
          "_date_raw": "1993/08/01"
        },
        {
          "rank": 3,
          "value": 21.4,
          "date": "1977年8月（昭和52年）",
          "_date_raw": "1977/08/01"
        },
        {
          "rank": 4,
          "value": 21.6,
          "date": "1996年8月（平成8年）",
          "_date_raw": "1996/08/01"
        },
        {
          "rank": 5,
          "value": 21.6,
          "date": "1991年8月（平成3年）",
          "_date_raw": "1991/08/01"
        },
        {
          "rank": 6,
          "value": 21.8,
          "date": "2004年8月（平成16年）",
          "_date_raw": "2004/08/01"
        },
        {
          "rank": 7,
          "value": 21.8,
          "date": "2003年8月（平成15年）",
          "_date_raw": "2003/08/01"
        },
        {
          "rank": 8,
          "value": 21.9,
          "date": "1981年8月（昭和56年）",
          "_date_raw": "1981/08/01"
        },
        {
          "rank": 9,
          "value": 22,
          "date": "2009年8月（平成21年）",
          "_date_raw": "2009/08/01"
        },
        {
          "rank": 10,
          "value": 22.1,
          "date": "2008年8月（平成20年）",
          "_date_raw": "2008/08/01"
        }
      ]
    },
    {
      "stationName": "米沢",
      "startDate": "1976年8月（昭和51年）",
      "ranks": [
        {
          "rank": 1,
          "value": 20.7,
          "date": "1980年8月（昭和55年）",
          "_date_raw": "1980/08/01"
        },
        {
          "rank": 2,
          "value": 20.8,
          "date": "1976年8月（昭和51年）",
          "_date_raw": "1976/08/01"
        },
        {
          "rank": 3,
          "value": 21.7,
          "date": "1993年8月（平成5年）",
          "_date_raw": "1993/08/01"
        },
        {
          "rank": 4,
          "value": 22.5,
          "date": "1977年8月（昭和52年）",
          "_date_raw": "1977/08/01"
        },
        {
          "rank": 5,
          "value": 23,
          "date": "2009年8月（平成21年）",
          "_date_raw": "2009/08/01"
        },
        {
          "rank": 6,
          "value": 23,
          "date": "1991年8月（平成3年）",
          "_date_raw": "1991/08/01"
        },
        {
          "rank": 7,
          "value": 23.1,
          "date": "2008年8月（平成20年）",
          "_date_raw": "2008/08/01"
        },
        {
          "rank": 8,
          "value": 23.4,
          "date": "2003年8月（平成15年）",
          "_date_raw": "2003/08/01"
        },
        {
          "rank": 9,
          "value": 23.4,
          "date": "1998年8月（平成10年）",
          "_date_raw": "1998/08/01"
        },
        {
          "rank": 10,
          "value": 23.4,
          "date": "1996年8月（平成8年）",
          "_date_raw": "1996/08/01"
        }
      ]
    }
  ]
}
