{
  "updatedAt": "2026-05-05T07:16:12.324079+09:00",
  "observedLatestAt": "2026-05-05T07:00:00+09:00",
  "prefecture": "神奈川県",
  "region": "関東甲信",
  "element": "monthMax12hPrecip",
  "month": "11",
  "rows": [
    {
      "stationName": "相模湖",
      "startDate": "1976年11月（昭和51年）",
      "ranks": [
        {
          "rank": 1,
          "value": 150,
          "date": "1990年11月30日（平成2年）",
          "_date_raw": "1990/11/30"
        },
        {
          "rank": 2,
          "value": 103,
          "date": "1993年11月14日（平成5年）",
          "_date_raw": "1993/11/14"
        },
        {
          "rank": 3,
          "value": 80,
          "date": "2000年11月2日（平成12年）",
          "_date_raw": "2000/11/02"
        },
        {
          "rank": 4,
          "value": 76,
          "date": "1997年11月30日（平成9年）",
          "_date_raw": "1997/11/30"
        },
        {
          "rank": 5,
          "value": 71,
          "date": "2003年11月25日（平成15年）",
          "_date_raw": "2003/11/25"
        },
        {
          "rank": 6,
          "value": 71,
          "date": "1982年11月30日（昭和57年）",
          "_date_raw": "1982/11/30"
        },
        {
          "rank": 7,
          "value": 68,
          "date": "1977年11月17日（昭和52年）",
          "_date_raw": "1977/11/17"
        },
        {
          "rank": 8,
          "value": 64,
          "date": "1981年11月2日（昭和56年）",
          "_date_raw": "1981/11/02"
        },
        {
          "rank": 9,
          "value": 63,
          "date": "1980年11月22日（昭和55年）",
          "_date_raw": "1980/11/22"
        },
        {
          "rank": 10,
          "value": 62,
          "date": "1979年11月11日（昭和54年）",
          "_date_raw": "1979/11/11"
        }
      ]
    },
    {
      "stationName": "相模原中央",
      "startDate": "1976年11月（昭和51年）",
      "ranks": [
        {
          "rank": 1,
          "value": 158,
          "date": "1990年11月30日（平成2年）",
          "_date_raw": "1990/11/30"
        },
        {
          "rank": 2,
          "value": 114,
          "date": "1993年11月14日（平成5年）",
          "_date_raw": "1993/11/14"
        },
        {
          "rank": 3,
          "value": 107,
          "date": "1982年11月30日（昭和57年）",
          "_date_raw": "1982/11/30"
        },
        {
          "rank": 4,
          "value": 76,
          "date": "2000年11月21日（平成12年）",
          "_date_raw": "2000/11/21"
        },
        {
          "rank": 5,
          "value": 75,
          "date": "1980年11月22日（昭和55年）",
          "_date_raw": "1980/11/22"
        },
        {
          "rank": 6,
          "value": 68,
          "date": "1997年11月30日（平成9年）",
          "_date_raw": "1997/11/30"
        },
        {
          "rank": 7,
          "value": 67,
          "date": "2003年11月25日（平成15年）",
          "_date_raw": "2003/11/25"
        },
        {
          "rank": 8,
          "value": 67,
          "date": "1979年11月11日（昭和54年）",
          "_date_raw": "1979/11/11"
        },
        {
          "rank": 9,
          "value": 67,
          "date": "1977年11月17日（昭和52年）",
          "_date_raw": "1977/11/17"
        },
        {
          "rank": 10,
          "value": 62,
          "date": "2021年11月9日（令和3年）",
          "_date_raw": "2021/11/09"
        }
      ]
    },
    {
      "stationName": "日吉",
      "startDate": "1976年11月（昭和51年）",
      "ranks": [
        {
          "rank": 1,
          "value": 134,
          "date": "1993年11月14日（平成5年）",
          "_date_raw": "1993/11/14"
        },
        {
          "rank": 2,
          "value": 111,
          "date": "1990年11月30日（平成2年）",
          "_date_raw": "1990/11/30"
        },
        {
          "rank": 3,
          "value": 80,
          "date": "2009年11月11日（平成21年）",
          "_date_raw": "2009/11/11"
        },
        {
          "rank": 4,
          "value": 77,
          "date": "1977年11月17日（昭和52年）",
          "_date_raw": "1977/11/17"
        },
        {
          "rank": 5,
          "value": 75,
          "date": "1980年11月22日（昭和55年）",
          "_date_raw": "1980/11/22"
        },
        {
          "rank": 6,
          "value": 72.5,
          "date": "2012年11月17日（平成24年）",
          "_date_raw": "2012/11/17"
        },
        {
          "rank": 7,
          "value": 72,
          "date": "2011年11月19日（平成23年）",
          "_date_raw": "2011/11/19"
        },
        {
          "rank": 8,
          "value": 68,
          "date": "1992年11月20日（平成4年）",
          "_date_raw": "1992/11/20"
        },
        {
          "rank": 9,
          "value": 64,
          "date": "1991年11月28日（平成3年）",
          "_date_raw": "1991/11/28"
        },
        {
          "rank": 10,
          "value": 63,
          "date": "2003年11月30日（平成15年）",
          "_date_raw": "2003/11/30"
        }
      ]
    },
    {
      "stationName": "丹沢湖",
      "startDate": "1976年11月（昭和51年）",
      "ranks": [
        {
          "rank": 1,
          "value": 156,
          "date": "2000年11月2日（平成12年）",
          "_date_raw": "2000/11/02"
        },
        {
          "rank": 2,
          "value": 120,
          "date": "1997年11月30日（平成9年）",
          "_date_raw": "1997/11/30"
        },
        {
          "rank": 3,
          "value": 117,
          "date": "1993年11月14日（平成5年）",
          "_date_raw": "1993/11/14"
        },
        {
          "rank": 4,
          "value": 115,
          "date": "1982年11月30日（昭和57年）",
          "_date_raw": "1982/11/30"
        },
        {
          "rank": 5,
          "value": 110,
          "date": "1999年11月1日（平成11年）",
          "_date_raw": "1999/11/01"
        },
        {
          "rank": 6,
          "value": 107,
          "date": "1990年11月30日（平成2年）",
          "_date_raw": "1990/11/30"
        },
        {
          "rank": 7,
          "value": 96,
          "date": "2024年11月2日（令和6年）",
          "_date_raw": "2024/11/02"
        },
        {
          "rank": 8,
          "value": 96,
          "date": "2011年11月19日（平成23年）",
          "_date_raw": "2011/11/19"
        },
        {
          "rank": 9,
          "value": 85,
          "date": "1977年11月17日（昭和52年）",
          "_date_raw": "1977/11/17"
        },
        {
          "rank": 10,
          "value": 75,
          "date": "1981年11月2日（昭和56年）",
          "_date_raw": "1981/11/02"
        }
      ]
    },
    {
      "stationName": "海老名",
      "startDate": "1976年11月（昭和51年）",
      "ranks": [
        {
          "rank": 1,
          "value": 140,
          "date": "1990年11月30日（平成2年）",
          "_date_raw": "1990/11/30"
        },
        {
          "rank": 2,
          "value": 133,
          "date": "1993年11月14日（平成5年）",
          "_date_raw": "1993/11/14"
        },
        {
          "rank": 3,
          "value": 102,
          "date": "1977年11月17日（昭和52年）",
          "_date_raw": "1977/11/17"
        },
        {
          "rank": 4,
          "value": 81,
          "date": "1997年11月30日（平成9年）",
          "_date_raw": "1997/11/30"
        },
        {
          "rank": 5,
          "value": 78,
          "date": "2009年11月11日（平成21年）",
          "_date_raw": "2009/11/11"
        },
        {
          "rank": 6,
          "value": 75,
          "date": "1982年11月30日（昭和57年）",
          "_date_raw": "1982/11/30"
        },
        {
          "rank": 7,
          "value": 74,
          "date": "1980年11月22日（昭和55年）",
          "_date_raw": "1980/11/22"
        },
        {
          "rank": 8,
          "value": 73,
          "date": "1991年11月28日（平成3年）",
          "_date_raw": "1991/11/28"
        },
        {
          "rank": 9,
          "value": 72.5,
          "date": "2021年11月9日（令和3年）",
          "_date_raw": "2021/11/09"
        },
        {
          "rank": 10,
          "value": 72,
          "date": "1992年11月20日（平成4年）",
          "_date_raw": "1992/11/20"
        }
      ]
    },
    {
      "stationName": "横浜",
      "startDate": "1976年11月（昭和51年）",
      "ranks": [
        {
          "rank": 1,
          "value": 130,
          "date": "1993年11月14日（平成5年）",
          "_date_raw": "1993/11/14"
        },
        {
          "rank": 2,
          "value": 112,
          "date": "1990年11月30日（平成2年）",
          "_date_raw": "1990/11/30"
        },
        {
          "rank": 3,
          "value": 97,
          "date": "1977年11月17日（昭和52年）",
          "_date_raw": "1977/11/17"
        },
        {
          "rank": 4,
          "value": 96.5,
          "date": "2011年11月19日（平成23年）",
          "_date_raw": "2011/11/19"
        },
        {
          "rank": 5,
          "value": 92.5,
          "date": "2009年11月11日（平成21年）",
          "_date_raw": "2009/11/11"
        },
        {
          "rank": 6,
          "value": 88,
          "date": "1992年11月20日（平成4年）",
          "_date_raw": "1992/11/20"
        },
        {
          "rank": 7,
          "value": 86,
          "date": "1980年11月22日（昭和55年）",
          "_date_raw": "1980/11/22"
        },
        {
          "rank": 8,
          "value": 82,
          "date": "1991年11月28日（平成3年）",
          "_date_raw": "1991/11/28"
        },
        {
          "rank": 9,
          "value": 79,
          "date": "2021年11月9日（令和3年）",
          "_date_raw": "2021/11/09"
        },
        {
          "rank": 10,
          "value": 69,
          "date": "2024年11月27日（令和6年）",
          "_date_raw": "2024/11/27"
        }
      ]
    },
    {
      "stationName": "平塚",
      "startDate": "1976年11月（昭和51年）",
      "ranks": [
        {
          "rank": 1,
          "value": 121,
          "date": "1993年11月14日（平成5年）",
          "_date_raw": "1993/11/14"
        },
        {
          "rank": 2,
          "value": 112,
          "date": "1977年11月17日（昭和52年）",
          "_date_raw": "1977/11/17"
        },
        {
          "rank": 3,
          "value": 104,
          "date": "1990年11月30日（平成2年）",
          "_date_raw": "1990/11/30"
        },
        {
          "rank": 4,
          "value": 79,
          "date": "1982年11月30日（昭和57年）",
          "_date_raw": "1982/11/30"
        },
        {
          "rank": 5,
          "value": 76,
          "date": "1991年11月28日（平成3年）",
          "_date_raw": "1991/11/28"
        },
        {
          "rank": 6,
          "value": 73,
          "date": "1997年11月29日（平成9年）",
          "_date_raw": "1997/11/29"
        },
        {
          "rank": 7,
          "value": 70.5,
          "date": "2021年11月9日（令和3年）",
          "_date_raw": "2021/11/09"
        },
        {
          "rank": 8,
          "value": 70,
          "date": "2009年11月11日（平成21年）",
          "_date_raw": "2009/11/11"
        },
        {
          "rank": 9,
          "value": 65,
          "date": "1980年11月22日（昭和55年）",
          "_date_raw": "1980/11/22"
        },
        {
          "rank": 10,
          "value": 64,
          "date": "2003年11月30日（平成15年）",
          "_date_raw": "2003/11/30"
        }
      ]
    },
    {
      "stationName": "辻堂",
      "startDate": "1992年11月（平成4年）",
      "ranks": [
        {
          "rank": 1,
          "value": 184,
          "date": "1993年11月14日（平成5年）",
          "_date_raw": "1993/11/14"
        },
        {
          "rank": 2,
          "value": 107.5,
          "date": "2021年11月9日（令和3年）",
          "_date_raw": "2021/11/09"
        },
        {
          "rank": 3,
          "value": 75.5,
          "date": "2011年11月19日（平成23年）",
          "_date_raw": "2011/11/19"
        },
        {
          "rank": 4,
          "value": 73,
          "date": "2009年11月11日（平成21年）",
          "_date_raw": "2009/11/11"
        },
        {
          "rank": 5,
          "value": 70,
          "date": "1992年11月20日（平成4年）",
          "_date_raw": "1992/11/20"
        },
        {
          "rank": 6,
          "value": 67.5,
          "date": "2024年11月27日（令和6年）",
          "_date_raw": "2024/11/27"
        },
        {
          "rank": 7,
          "value": 67,
          "date": "2003年11月30日（平成15年）",
          "_date_raw": "2003/11/30"
        },
        {
          "rank": 8,
          "value": 65,
          "date": "2000年11月21日（平成12年）",
          "_date_raw": "2000/11/21"
        },
        {
          "rank": 9,
          "value": 62,
          "date": "1999年11月1日（平成11年）",
          "_date_raw": "1999/11/01"
        },
        {
          "rank": 10,
          "value": 49,
          "date": "2001年11月6日（平成13年）",
          "_date_raw": "2001/11/06"
        }
      ]
    },
    {
      "stationName": "箱根",
      "startDate": "1976年11月（昭和51年）",
      "ranks": [
        {
          "rank": 1,
          "value": 217.5,
          "date": "2011年11月19日（平成23年）",
          "_date_raw": "2011/11/19"
        },
        {
          "rank": 2,
          "value": 206,
          "date": "1990年11月30日（平成2年）",
          "_date_raw": "1990/11/30"
        },
        {
          "rank": 3,
          "value": 171,
          "date": "1977年11月17日（昭和52年）",
          "_date_raw": "1977/11/17"
        },
        {
          "rank": 4,
          "value": 153.5,
          "date": "2024年11月2日（令和6年）",
          "_date_raw": "2024/11/02"
        },
        {
          "rank": 5,
          "value": 143,
          "date": "2000年11月21日（平成12年）",
          "_date_raw": "2000/11/21"
        },
        {
          "rank": 6,
          "value": 139,
          "date": "2022年11月30日（令和4年）",
          "_date_raw": "2022/11/30"
        },
        {
          "rank": 7,
          "value": 135,
          "date": "1997年11月30日（平成9年）",
          "_date_raw": "1997/11/30"
        },
        {
          "rank": 8,
          "value": 135,
          "date": "1992年11月20日（平成4年）",
          "_date_raw": "1992/11/20"
        },
        {
          "rank": 9,
          "value": 133,
          "date": "1993年11月13日（平成5年）",
          "_date_raw": "1993/11/13"
        },
        {
          "rank": 10,
          "value": 115,
          "date": "2004年11月12日（平成16年）",
          "_date_raw": "2004/11/12"
        }
      ]
    },
    {
      "stationName": "小田原",
      "startDate": "1976年11月（昭和51年）",
      "ranks": [
        {
          "rank": 1,
          "value": 122,
          "date": "1982年11月30日（昭和57年）",
          "_date_raw": "1982/11/30"
        },
        {
          "rank": 2,
          "value": 121,
          "date": "1993年11月14日（平成5年）",
          "_date_raw": "1993/11/14"
        },
        {
          "rank": 3,
          "value": 110,
          "date": "1990年11月30日（平成2年）",
          "_date_raw": "1990/11/30"
        },
        {
          "rank": 4,
          "value": 109,
          "date": "1977年11月17日（昭和52年）",
          "_date_raw": "1977/11/17"
        },
        {
          "rank": 5,
          "value": 103.5,
          "date": "2011年11月19日（平成23年）",
          "_date_raw": "2011/11/19"
        },
        {
          "rank": 6,
          "value": 94.5,
          "date": "2024年11月2日（令和6年）",
          "_date_raw": "2024/11/02"
        },
        {
          "rank": 7,
          "value": 91,
          "date": "2000年11月2日（平成12年）",
          "_date_raw": "2000/11/02"
        },
        {
          "rank": 8,
          "value": 91,
          "date": "1997年11月30日（平成9年）",
          "_date_raw": "1997/11/30"
        },
        {
          "rank": 9,
          "value": 84,
          "date": "1980年11月22日（昭和55年）",
          "_date_raw": "1980/11/22"
        },
        {
          "rank": 10,
          "value": 78,
          "date": "1981年11月3日（昭和56年）",
          "_date_raw": "1981/11/03"
        }
      ]
    },
    {
      "stationName": "三浦",
      "startDate": "1976年11月（昭和51年）",
      "ranks": [
        {
          "rank": 1,
          "value": 161,
          "date": "1977年11月17日（昭和52年）",
          "_date_raw": "1977/11/17"
        },
        {
          "rank": 2,
          "value": 155,
          "date": "1993年11月14日（平成5年）",
          "_date_raw": "1993/11/14"
        },
        {
          "rank": 3,
          "value": 114,
          "date": "1990年11月30日（平成2年）",
          "_date_raw": "1990/11/30"
        },
        {
          "rank": 4,
          "value": 113,
          "date": "2012年11月6日（平成24年）",
          "_date_raw": "2012/11/06"
        },
        {
          "rank": 5,
          "value": 110,
          "date": "1994年11月19日（平成6年）",
          "_date_raw": "1994/11/19"
        },
        {
          "rank": 6,
          "value": 95,
          "date": "1985年11月7日（昭和60年）",
          "_date_raw": "1985/11/07"
        },
        {
          "rank": 7,
          "value": 89,
          "date": "2004年11月12日（平成16年）",
          "_date_raw": "2004/11/12"
        },
        {
          "rank": 8,
          "value": 78,
          "date": "1991年11月8日（平成3年）",
          "_date_raw": "1991/11/08"
        },
        {
          "rank": 9,
          "value": 77,
          "date": "1980年11月22日（昭和55年）",
          "_date_raw": "1980/11/22"
        },
        {
          "rank": 10,
          "value": 75.5,
          "date": "2021年11月9日（令和3年）",
          "_date_raw": "2021/11/09"
        }
      ]
    }
  ]
}
